latinisation/__init__.py
latinisation/armenian.py
latinisation-0.0.1.dist-info/LICENSE
latinisation-0.0.1.dist-info/METADATA
latinisation-0.0.1.dist-info/WHEEL
latinisation-0.0.1.dist-info/top_level.txt
latinisation-0.0.1.dist-info/RECORD
