Metadata-Version: 2.1
Name: latinisation
Version: 0.0.1
Summary: Latinisation of different alphabets.
Home-page: https://github.com/AAVVIronAlex/latinisation-api
Author: Alex Babajanyan
Author-email: alex.babajanyan2015@gmail.com
Classifier: Programming Language :: Python :: 3
Classifier: License :: OSI Approved :: MIT License
Classifier: Operating System :: OS Independent
Requires-Python: >=3.7
License-File: LICENSE
